MilkyWaySeeker/CoordsConversion.py
MilkyWaySeeker/DataFileConversion.py
MilkyWaySeeker/StellarParameterConversion.py
MilkyWaySeeker/__init__.py
MilkyWaySeeker/ploth.py
MilkyWaySeeker-0.0.2.dist-info/METADATA
MilkyWaySeeker-0.0.2.dist-info/WHEEL
MilkyWaySeeker-0.0.2.dist-info/top_level.txt
MilkyWaySeeker-0.0.2.dist-info/RECORD
