Metadata-Version: 2.1
Name: MilkyWaySeeker
Version: 0.0.2
Summary: A tool of htian for studying the Milky Way
Author: htian_astro
Author-email: htian_astro@163.com
